TennisSpider
