Metadata-Version: 1.0
Name: TennisSpider
Version: 0.31
Summary: Package for parsing info about tennis results and stats.
Home-page: https://github.com/cs-hse-projects/DataSpider_Dubov
Author: Dmitry Dubov
Author-email: dmitry.s.dubov@gmail.com
License: PSF
Keywords: Tennis,Results
Platform: UNKNOWN
